<?xml version="1.0" encoding="utf-8"?>
<Entity parent="template_structure_economic_market">
  <Footprint>
    <Square width="36.0" depth="30.0"/>
    <Height>8.0</Height>
  </Footprint>
  <Health>
    <SpawnEntityOnDeath>decay|rubble/rubble_stone_6x6</SpawnEntityOnDeath>
  </Health>
  <Identity>
    <Civ>rome</Civ>
    <SpecificName>Mercātus</SpecificName>
  </Identity>
    <Promotion>
    <Entity>structures/rome/market_2</Entity>
    <RequiredXp>3000</RequiredXp>
  </Promotion>
       <Trainer>
    <BatchTimeModifier>0.7</BatchTimeModifier>
    <Entities datatype="tokens">
      -units/{civ}/merc_inf_slinger_market_b
      units/{civ}/merc_inf_slinger_market_a
      -units/{civ}/merc_inf_archer_market_b
      units/{civ}/merc_inf_archer_market_a
    </Entities>
  </Trainer>
  <Obstruction>
    <Static width="32.0" depth="26.0"/>
  </Obstruction>
  <VisualActor>
    <Actor>structures/romans/market.xml</Actor>
    <FoundationActor>structures/fndn_9x7.xml</FoundationActor>
  </VisualActor>
</Entity>
