<?xml version="1.0" encoding="utf-8"?>
<Entity parent="template_unit_champion_cavalry_archer">
  <Attack>
    <Ranged>
      <AttackName>Bow</AttackName>
      <Damage>
        <Pierce>13.5</Pierce>
      </Damage>
      <MaxRange>70</MaxRange>
      <PrepareTime>0</PrepareTime>
      <RepeatTime>1100</RepeatTime>
      <Projectile>
        <Speed>125</Speed>
        <Spread>1.5</Spread>
        <Gravity>50</Gravity>
        <FriendlyFire>false</FriendlyFire>
        <LaunchPoint y="5"/>
      </Projectile>
      <PreferredClasses datatype="tokens">Human</PreferredClasses>
    </Ranged>
  </Attack>
   <Cost>
    <Population>2</Population>
    <BuildTime>30</BuildTime>
    <Resources>
      <food>225</food>
      <wood>100</wood>
      <metal>225</metal>
    </Resources>
  </Cost>
  <BuildingAI>
    <DefaultArrowCount>1</DefaultArrowCount>
    <GarrisonArrowMultiplier>1</GarrisonArrowMultiplier>
    <GarrisonArrowClasses>Archer</GarrisonArrowClasses>
    <MaxArrowCount>1</MaxArrowCount>
  </BuildingAI>
  <Identity>
    <VisibleClasses datatype="tokens">Ranged Archer</VisibleClasses>
    <GenericName>Champion Chariot Archer</GenericName>
     <Requirements>
      <Techs datatype="tokens">unlock_champion_chariots</Techs>
    </Requirements>
  </Identity>
  <Loot>
    <metal op="add">10</metal>
  </Loot>
  <Sound>
    <SoundGroups>
      <attack_impact_ranged>attack/impact/arrow_impact.xml</attack_impact_ranged>
      <attack_ranged>attack/weapon/bow_attack.xml</attack_ranged>
    </SoundGroups>
  </Sound>
  <UnitAI>
    <Formations datatype="tokens">
      special/formations/skirmish
    </Formations>
  </UnitAI>
</Entity>
